{
 "stat": [
  {
   "date": "2025-12-02",
   "n_vegan_friendly": 39656,
   "n_vegan_limited": 878,
   "n_vegan_only": 3610,
   "n_vegetarian_friendly": 57448,
   "n_vegetarian_only": 2183
  },
  {
   "date": "2025-12-08",
   "n_vegan_friendly": 142,
   "n_vegan_limited": 30,
   "n_vegan_only": 6,
   "n_vegetarian_friendly": 0,
   "n_vegetarian_only": 10
  },
  {
   "date": "2025-12-09",
   "n_vegan_friendly": 142,
   "n_vegan_limited": 30,
   "n_vegan_only": 6,
   "n_vegetarian_friendly": 0,
   "n_vegetarian_only": 10
  },
  {
   "date": "2025-12-22",
   "n_vegan_friendly": 142,
   "n_vegan_limited": 30,
   "n_vegan_only": 6,
   "n_vegetarian_friendly": 0,
   "n_vegetarian_only": 10
  },
  {
   "date": "2026-01-01",
   "n_vegan_friendly": 141,
   "n_vegan_limited": 30,
   "n_vegan_only": 6,
   "n_vegetarian_friendly": 0,
   "n_vegetarian_only": 10
  },
  {
   "date": "2026-01-08",
   "n_vegan_friendly": 141,
   "n_vegan_limited": 30,
   "n_vegan_only": 6,
   "n_vegetarian_friendly": 0,
   "n_vegetarian_only": 10
  }
 ]
}